pylero/__init__.py
pylero/_compatible.py
pylero/activity.py
pylero/activity_comment.py
pylero/activity_custom_value.py
pylero/activity_custom_value_entry.py
pylero/activity_source.py
pylero/approval.py
pylero/attachment.py
pylero/base_polarion.py
pylero/baseline.py
pylero/build.py
pylero/build_linked_work_item.py
pylero/build_test_results.py
pylero/category.py
pylero/change.py
pylero/comment.py
pylero/custom.py
pylero/custom_field.py
pylero/custom_field_type.py
pylero/document.py
pylero/enum_custom_field_type.py
pylero/enum_option.py
pylero/enum_option_id.py
pylero/exceptions.py
pylero/externally_linked_work_item.py
pylero/field_diff.py
pylero/hyperlink.py
pylero/imported_comment.py
pylero/language_definition.py
pylero/license_info.py
pylero/linked_work_item.py
pylero/module_comment.py
pylero/plan.py
pylero/plan_record.py
pylero/plan_statistics.py
pylero/planning_constraint.py
pylero/priority_opt.py
pylero/priority_option_id.py
pylero/product_license.py
pylero/project.py
pylero/project_group.py
pylero/properties.py
pylero/property.py
pylero/pylero.cfg
pylero/revision.py
pylero/server.py
pylero/session.py
pylero/signature.py
pylero/signature_context.py
pylero/signature_data.py
pylero/subterra_uri.py
pylero/test_record.py
pylero/test_run.py
pylero/test_run_attachment.py
pylero/test_step.py
pylero/test_step_result.py
pylero/test_steps.py
pylero/tests_configuration.py
pylero/text.py
pylero/time_point.py
pylero/user.py
pylero/wiki_page.py
pylero/wiki_page_attachment.py
pylero/work_item.py
pylero/work_record.py
pylero/workflow_action.py
pylero/cli/__init__.py
pylero/cli/cmd.py
pylero-0.2.0.data/scripts/pylero
pylero-0.2.0.data/scripts/pylero-cmd
pylero-0.2.0.dist-info/licenses/LICENSE
pylero-0.2.0.dist-info/METADATA
pylero-0.2.0.dist-info/WHEEL
pylero-0.2.0.dist-info/top_level.txt
pylero-0.2.0.dist-info/RECORD
